cis_checks_8/__init__.py
cis_checks_8/iam_control_1.py
cis_checks_8/logging_control_2.py
cis_checks_8/monitoring_control_3.py
cis_checks_8/networking_control_4.py
cis_checks_8/security_control_5.py
cis_checks_8/utils.py
cis_checks_8-0.0.9.dist-info/METADATA
cis_checks_8-0.0.9.dist-info/WHEEL
cis_checks_8-0.0.9.dist-info/top_level.txt
cis_checks_8-0.0.9.dist-info/RECORD
